MANIFEST.in
README.rst
README.txt
bootstrap.py
buildout.cfg
setup.cfg
setup.py
test-4.2.x.cfg
test-4.3.x.cfg
travis.cfg
collective/__init__.py
collective.subscribablesections.egg-info/PKG-INFO
collective.subscribablesections.egg-info/SOURCES.txt
collective.subscribablesections.egg-info/dependency_links.txt
collective.subscribablesections.egg-info/entry_points.txt
collective.subscribablesections.egg-info/namespace_packages.txt
collective.subscribablesections.egg-info/not-zip-safe
collective.subscribablesections.egg-info/paster_plugins.txt
collective.subscribablesections.egg-info/requires.txt
collective.subscribablesections.egg-info/top_level.txt
collective/subscribablesections/__init__.py
collective/subscribablesections/config.py
collective/subscribablesections/configure.zcml
collective/subscribablesections/events.py
collective/subscribablesections/interfaces.py
collective/subscribablesections/manager.py
collective/subscribablesections/rebuild_i18n.sh
collective/subscribablesections/subtypes.py
collective/subscribablesections/testing.py
collective/subscribablesections/browser/__init__.py
collective/subscribablesections/browser/configure.zcml
collective/subscribablesections/browser/views/__init__.py
collective/subscribablesections/browser/views/manage.py
collective/subscribablesections/browser/views/request.py
collective/subscribablesections/browser/views/sections.py
collective/subscribablesections/browser/views/subscriptions.py
collective/subscribablesections/browser/views/templates/manage.pt
collective/subscribablesections/browser/views/templates/request.pt
collective/subscribablesections/browser/views/templates/subscriptions.pt
collective/subscribablesections/locales/NOT_EMPTY.txt
collective/subscribablesections/locales/collective.subscribablesections.pot
collective/subscribablesections/locales/manual.pot
collective/subscribablesections/locales/plone.pot
collective/subscribablesections/locales/en/LC_MESSAGES/README.txt
collective/subscribablesections/locales/en/LC_MESSAGES/collective.subscribablesections.po
collective/subscribablesections/locales/en/LC_MESSAGES/plone.po
collective/subscribablesections/locales/es/LC_MESSAGES/README.txt
collective/subscribablesections/locales/es/LC_MESSAGES/collective.subscribablesections.po
collective/subscribablesections/locales/es/LC_MESSAGES/plone.po
collective/subscribablesections/locales/nl/LC_MESSAGES/README.txt
collective/subscribablesections/locales/nl/LC_MESSAGES/collective.subscribablesections.po
