Metadata-Version: 1.1
Name: collective.subscribablesections
Version: 1.1
Summary: Allow Members to request access to private Plone Folders.
Home-page: http://plone.org/products/collective.subscribablesections
Author: Kees Hink
Author-email: keeshink@gmail.com
License: GPL
Keywords: subscribable sections private Plone folder
Platform: UNKNOWN
Classifier: Development Status :: 3 - Alpha
Classifier: Environment :: Web Environment
Classifier: Framework :: Plone
Classifier: Framework :: Plone :: 4.2
Classifier: Framework :: Plone :: 4.3
Classifier: Intended Audience :: End Users/Desktop
Classifier: License :: OSI Approved :: GNU General Public License (GPL)
Classifier: Operating System :: OS Independent
Classifier: Programming Language :: Python
Classifier: Programming Language :: Python :: 2.6
Classifier: Programming Language :: Python :: 2.7
Classifier: Topic :: Office/Business :: Groupware
Classifier: Topic :: Software Development :: Libraries :: Python Modules
